[{"id_history":1,"id_contribuable":"","motif":"connexion","comment":"","date_history":"2024-06-12T02:10:28.642Z"},{"id_history":2,"id_contribuable":"74lDaYRrC3","id_user":1,"motif":"Validation contribuable","comment":"","date_history":"2024-06-12T02:12:53.321Z"},{"id_history":3,"id_contribuable":"OEOz9HCc","id_user":1,"motif":"Validation contribuable","comment":"","date_history":"2024-06-12T02:20:40.597Z"},{"id_history":4,"id_contribuable":"OEOz9HCc","id_user":1,"motif":"Blockage de contribuable dont la reference fiscal est : 000000000003","comment":"blocage","date_history":"2024-06-12T02:25:10.902Z"},{"id_history":5,"id_contribuable":"OEOz9HCc","id_user":1,"comment":"deblocage","motif":"deblocage","date_history":"2024-06-12T02:26:41.963Z"},{"id_history":6,"id_contribuable":"74lDaYRrC3","id_user":1,"motif":"Cessation de l'activité du contribuable 74lDaYRrC3","comment":"cessation","date_history":"2024-06-12T02:29:59.327Z"},{"id_history":7,"id_contribuable":"74lDaYRrC3","id_user":1,"motif":"reprise","comment":"reprise","date_history":"2024-06-12T02:30:41.464Z"},{"id_history":8,"id_contribuable":"","motif":"connexion","comment":"","date_history":"2024-06-12T09:25:08.130Z"},{"id_history":9,"id_contribuable":"","motif":"connexion","comment":"","date_history":"2024-06-14T05:36:00.867Z"}]