[{"id":"NOewonMZFL","raison_social":"Randriamantena Lalatina","reference_fiscal":"000000000001","type":"Personne physique","situation_matrimoiniale":"Célibataire","cin":"213098765412","sexe":"Feminin","etranger":false,"numero_passeport":"","date_de_delivrance_passeport":"","date_de_delivrance_cin":"2024-01-11","lieu_de_delivrance_cin":"Mandritsara","date_de_naissance":"1996-01-14","lieu_de_naissance":"Antsohihy","forme_juridique":"Forme ","regime_fiscal":"Regime fiscal","date_agrement":"","reference_agrement":"","periode_grace":"periode","date_creation":"2024-01-10","capital":"Capital","RIB":"Disponible","actif":true,"actionnaire":[],"dirigeant":[],"coordonnees":null,"etablissement":[],"mot_de_passe":"$2lWZgvC_","vehicule":[],"assujetissement":[]},{"id":"SBmpDkbIf","raison_social":"","reference_fiscal":"000000000002","type":"","situation_matrimoiniale":"","cin":"","sexe":"","etranger":false,"numero_passeport":"","date_de_delivrance_passeport":"","date_de_delivrance_cin":"","lieu_de_delivrance_cin":"","date_de_naissance":"","lieu_de_naissance":"","forme_juridique":"","regime_fiscal":"","date_agrement":"","reference_agrement":"","periode_grace":"","date_creation":"","capital":"","RIB":"","numero_compte_bancaire":"","actif":false}]