[
    {
        "id": "1",
        "id_contribuable": "1hTCkfLov",
        "nom_commercial": "Nom commercial",
        "activite": "Entreprenariat",
        "titre": "Boite developpeur",
        "date_ouverture": "2024-01-27",
        "adresse": "avenue 309 Majunga be",
        "fokontany": "Majunga be",
        "province": "Mahajanga",
        "region": "Boeny",
        "district": "Mahajanga",
        "commune": "Mahajanga",
        "telephone_1": "+261329539505",
        "autre_telephone": "+261344544505",
        "fax": "fax",
        "email": "Baobab@gmail.com",
        "exportateur": true,
        "importateur": false,
        "proprietaire_local": true
    },
    {
        "id": "1",
        "id_contribuable": "K0BQuRH3",
        "nom_commercial": "nom",
        "activite": "act",
        "titre": "titre",
        "date_ouverture": "2024-01-10",
        "adresse": "adresse",
        "fokontany": "fokontany",
        "province": "province",
        "region": "region",
        "district": "district",
        "commune": "commune",
        "telephone_1": "telephone",
        "autre_telephone": "tel",
        "fax": "fax",
        "email": "email",
        "exportateur": false,
        "importateur": false,
        "proprietaire_local": false
    },
    {
        "id": "1",
        "id_contribuable": "fQ1v0iW0",
        "nom_commercial": "garnd entrepot ",
        "activite": "vendeur",
        "titre": "Service libre",
        "date_ouverture": "2024-01-11",
        "adresse": "lot 230J096",
        "fokontany": "Ambohimandamina",
        "province": "Mahajanga",
        "region": "Boeny",
        "district": "Mahajanga 1",
        "commune": "Mahajanga",
        "telephone_1": "+261098567",
        "autre_telephone": "+21998765",
        "fax": "Garge",
        "email": "thetitre@gmail.com",
        "exportateur": false,
        "importateur": false,
        "proprietaire_local": false
    }
]